ray_utilities/__init__.py
ray_utilities/_runtime_constants.py
ray_utilities/constants.py
ray_utilities/discrete_evaluation.py
ray_utilities/dummy_encoder.py
ray_utilities/misc.py
ray_utilities/nice_logger.py
ray_utilities/postprocessing.py
ray_utilities/random.py
ray_utilities/temp_dir.py
ray_utilities/testing_utils.py
ray_utilities/warn.py
ray_utilities/callbacks/__init__.py
ray_utilities/callbacks/comet.py
ray_utilities/callbacks/progress_bar.py
ray_utilities/callbacks/upload_helper.py
ray_utilities/callbacks/wandb.py
ray_utilities/callbacks/_wandb_monitor/__init__.py
ray_utilities/callbacks/_wandb_monitor/_wandb_selenium_login.py
ray_utilities/callbacks/_wandb_monitor/_wandb_selenium_login_mp.py
ray_utilities/callbacks/_wandb_monitor/_wandb_session_cache.py
ray_utilities/callbacks/_wandb_monitor/wandb_run_monitor.py
ray_utilities/callbacks/algorithm/__init__.py
ray_utilities/callbacks/algorithm/adjust_config_based_on_batch_size.py
ray_utilities/callbacks/algorithm/algo_metric_checkpointer.py
ray_utilities/callbacks/algorithm/callback_mixins.py
ray_utilities/callbacks/algorithm/discrete_eval_callback.py
ray_utilities/callbacks/algorithm/dynamic_batch_size.py
ray_utilities/callbacks/algorithm/dynamic_buffer_callback.py
ray_utilities/callbacks/algorithm/dynamic_evaluation_callback.py
ray_utilities/callbacks/algorithm/dynamic_hyperparameter.py
ray_utilities/callbacks/algorithm/env_render_callback.py
ray_utilities/callbacks/algorithm/exact_sampling_callback.py
ray_utilities/callbacks/algorithm/model_config_saver_callback.py
ray_utilities/callbacks/algorithm/reset_episode_metrics.py
ray_utilities/callbacks/algorithm/seeded_env_callback.py
ray_utilities/callbacks/tuner/__init__.py
ray_utilities/callbacks/tuner/_adv_wandb_logging_actor.py
ray_utilities/callbacks/tuner/_file_logger_fork_mixin.py
ray_utilities/callbacks/tuner/_log_result_grouping.py
ray_utilities/callbacks/tuner/_save_video_callback.py
ray_utilities/callbacks/tuner/adv_comet_callback.py
ray_utilities-0.7.0.dist-info/licenses/LICENSE
ray_utilities-0.7.0.dist-info/WHEEL
ray_utilities-0.7.0.dist-info/METADATA
ray_utilities-0.7.0.dist-info/RECORD
