Metadata-Version: 2.4
Name: ray_utilities
Version: 0.7.0
Summary: Utilities for Ray RLlib and related workflows. Includes experiment setup, callbacks, and JAX model utilities.
Author-email: Daniel Sperber <daniel.sperber@gmail.com>
Requires-Python: >=3.9
Classifier: Programming Language :: Python :: 3
Classifier: License :: OSI Approved :: MIT License
Classifier: Operating System :: OS Independent
Classifier: Intended Audience :: Developers
Classifier: Intended Audience :: Science/Research
Classifier: Topic :: Scientific/Engineering :: Artificial Intelligence
License-File: LICENSE
Requires-Dist: ray[tune, rllib] < 2.50.0
Requires-Dist: typed-argument-parser
Requires-Dist: tqdm
Requires-Dist: colorlog
Requires-Dist: opencv-python
Requires-Dist: python-dotenv
Requires-Dist: frozenlist
Requires-Dist: torch
Requires-Dist: comet_ml
Requires-Dist: wandb
Requires-Dist: optuna
Requires-Dist: jax
Requires-Dist: exceptiongroup; python_version < '3.11'
Requires-Dist: pybase62==1.0.0
Requires-Dist: typing_extensions >= 4.13
Requires-Dist: argcomplete ; extra == "argcomplete"
Requires-Dist: comet_ml ; extra == "comet"
Requires-Dist: jax ; extra == "jax"
Requires-Dist: flax ; extra == "jax"
Requires-Dist: optax ; extra == "jax"
Requires-Dist: chex ; extra == "jax"
Requires-Dist: optuna ; extra == "optuna"
Requires-Dist: pytest ; extra == "test"
Requires-Dist: pytest-timeout ; extra == "test"
Requires-Dist: pytest-subtests ; extra == "test"
Requires-Dist: debugpy ; extra == "test"
Requires-Dist: testfixtures ; extra == "test"
Requires-Dist: flaky ; extra == "test"
Requires-Dist: wandb>=0.16.5 ; extra == "wandb"
Requires-Dist: selenium>=4.15.0 ; extra == "wandb"
Provides-Extra: argcomplete
Provides-Extra: comet
Provides-Extra: jax
Provides-Extra: optuna
Provides-Extra: test
Provides-Extra: wandb
